interactive_script_py/__init__.py
interactive_script_py/command.py
interactive_script_py/response_handler.py
interactive_script_py/ui.py
interactive_script_py/utils.py
interactive_script_py/commands/clear.py
interactive_script_py/commands/console.py
interactive_script_py/commands/file_open.py
interactive_script_py/commands/file_open_folder.py
interactive_script_py/commands/file_save.py
interactive_script_py/commands/file_show_open.py
interactive_script_py/commands/file_show_open_folder.py
interactive_script_py/commands/file_show_save.py
interactive_script_py/commands/inline_confirm.py
interactive_script_py/commands/inline_date.py
interactive_script_py/commands/inline_select.py
interactive_script_py/commands/inline_text.py
interactive_script_py/commands/input_buttons.py
interactive_script_py/commands/input_checkboxes.py
interactive_script_py/commands/input_confirm.py
interactive_script_py/commands/input_date.py
interactive_script_py/commands/input_grid.py
interactive_script_py/commands/input_radioboxes.py
interactive_script_py/commands/input_select_record.py
interactive_script_py/commands/input_text.py
interactive_script_py/commands/log.py
interactive_script_py/commands/output.py
interactive_script_py/commands/output_clear.py
interactive_script_py/commands/output_grid.py
interactive_script_py/commands/output_progress.py
interactive_script_py/commands/output_text.py
interactive_script_py/commands/window_show_grid.py
interactive_script_py/commands/window_show_text.py
interactive_script_py/objects/progress.py
interactive_script_py/objects/styled_text.py
interactive_script_py/objects/styled_text_color.py
interactive_script_py-1.0.7.dist-info/licenses/LICENSE
interactive_script_py-1.0.7.dist-info/METADATA
interactive_script_py-1.0.7.dist-info/WHEEL
interactive_script_py-1.0.7.dist-info/top_level.txt
interactive_script_py-1.0.7.dist-info/RECORD
