Metadata-Version: 2.4
Name: interactive-script-py
Version: 1.0.7
Summary: A Python library to communicate with 'Interactive Script' VSCode extension.
Author: Andriy Viyatyk
Requires-Python: >=3.7
License-File: LICENSE
Dynamic: license-file
